tureng_cli/__init__.py
tureng_cli/__main__.py
tureng_cli/cli.py
tureng_cli/commands/__init__.py
tureng_cli/commands/sentence.py
tureng_cli/commands/synonym.py
tureng_cli/commands/translate.py
tureng_cli/utilities/__init__.py
tureng_cli/utilities/constants.py
tureng_cli/utilities/helpers.py
tureng_cli/utilities/sentence/__init__.py
tureng_cli/utilities/sentence/helpers.py
tureng_cli/utilities/synonym/__init__.py
tureng_cli/utilities/synonym/helpers.py
tureng_cli/utilities/translate/__init__.py
tureng_cli/utilities/translate/helpers.py
bs_tureng_cli-1.0.0.dist-info/LICENSE
bs_tureng_cli-1.0.0.dist-info/METADATA
bs_tureng_cli-1.0.0.dist-info/WHEEL
bs_tureng_cli-1.0.0.dist-info/entry_points.txt
bs_tureng_cli-1.0.0.dist-info/top_level.txt
bs_tureng_cli-1.0.0.dist-info/RECORD
