Metadata-Version: 2.1
Name: bs-tureng-cli
Version: 1.0.0
Summary: BaysanSoft Tureng CLI for EN-TR translation
Author: @mebaysan
Author-email: mail@mebaysan.com
License: MIT
Keywords: mebaysan translation Turkish English Tureng CLI
Classifier: Programming Language :: Python :: 3
Classifier: License :: OSI Approved :: MIT License
Classifier: Operating System :: OS Independent
Requires-Python: >=3.8
License-File: LICENSE
Requires-Dist: beautifulsoup4
Requires-Dist: click
Requires-Dist: requests
